pansy/__init__.py
pansy/blueprint.py
pansy/pansy.py
pansy/contrib/__init__.py
pansy/contrib/token/__init__.py
pansy/contrib/token/easy_aes.py
pansy/contrib/token/token_helper.py
pansy/master/__init__.py
pansy/master/master.py
pansy/proto/__init__.py
pansy/proto/pansy_pb2.py
pansy/share/__init__.py
pansy/share/config.py
pansy/share/constants.py
pansy/share/log.py
pansy/share/mixins.py
pansy/share/task.py
pansy/share/utils.py
pansy/station/__init__.py
pansy/station/station.py
pansy/trigger/__init__.py
pansy/trigger/client.py
pansy/trigger/trigger.py
pansy/worker/__init__.py
pansy/worker/connection.py
pansy/worker/request.py
pansy/worker/worker.py
pansy-2.0.31.dist-info/METADATA
pansy-2.0.31.dist-info/WHEEL
pansy-2.0.31.dist-info/top_level.txt
pansy-2.0.31.dist-info/RECORD
